sonse/__init__.py
sonse/__main__.py
sonse/clui.py
sonse/coms.py
sonse/fsys.py
sonse/jobs.py
sonse-1.0.2.dist-info/METADATA
sonse-1.0.2.dist-info/WHEEL
sonse-1.0.2.dist-info/entry_points.txt
sonse-1.0.2.dist-info/top_level.txt
sonse-1.0.2.dist-info/RECORD
