Metadata-Version: 2.1
Name: sonse
Version: 1.0.2
Summary: Stephen's Obsessive Note-Storage Engine.
Home-page: https://github.com/rattlerake/sonse
Author: Stephen Malone
Author-email: mail@sonse.org
License: UNKNOWN
Project-URL: Changelog, https://github.com/rattlerake/sonse/blob/main/changes.md
Project-URL: Issues, https://github.com/rattlerake/sonse/issues
Keywords: notes note-taking cli
Platform: UNKNOWN
Classifier: Development Status :: 3 - Alpha
Classifier: Environment :: Console
Classifier: Intended Audience :: End Users/Desktop
Classifier: License :: OSI Approved :: BSD License
Classifier: Natural Language :: English
Classifier: Programming Language :: Python :: 3.10
Classifier: Topic :: Office/Business :: News/Diary
Classifier: Topic :: Terminals
Classifier: Topic :: Utilities
Requires-Python: >=3.10
Requires-Dist: click (>=8.1)
